kpth/__init__.py
kpth/번역기.py
kpth/예약어.py
kpth/중앙.py
kptha-1.0.0.dist-info/licenses/LICENSE
kptha-1.0.0.dist-info/METADATA
kptha-1.0.0.dist-info/WHEEL
kptha-1.0.0.dist-info/entry_points.txt
kptha-1.0.0.dist-info/top_level.txt
kptha-1.0.0.dist-info/RECORD
