Metadata-Version: 2.4
Name: kptha
Version: 1.0.0
Summary: Korean-based Python syntax translator | 한국어 파이썬 번역기
Author: rainy58
Author-email: yhg4908@naver.com
Project-URL: Issues, https://github.com/yhg4908/kpth/issues
Project-URL: Repository, https://github.com/yhg4908/kpth
Keywords: korea korean python kpy kpth 한국어 한국 파이썬
Classifier: Development Status :: 2 - Pre-Alpha
Classifier: Intended Audience :: Developers
Classifier: License :: OSI Approved :: MIT License
Classifier: Programming Language :: Python :: 3.10
Classifier: Programming Language :: Python :: 3.11
Classifier: Programming Language :: Python :: 3.12
Classifier: Programming Language :: Python :: 3.13
Classifier: Natural Language :: Korean
Requires-Python: >=3.10
License-File: LICENSE
Dynamic: author
Dynamic: author-email
Dynamic: classifier
Dynamic: description
Dynamic: description-content-type
Dynamic: keywords
Dynamic: license-file
Dynamic: project-url
Dynamic: requires-python
Dynamic: summary
